[
  { "County": "Adams County", "State": "Pennsylvania" },
  { "County": "Allegheny County", "State": "Pennsylvania" },
  { "County": "Armstrong County", "State": "Pennsylvania" },
  { "County": "Beaver County", "State": "Pennsylvania" },
  { "County": "Bedford County", "State": "Pennsylvania" },
  { "County": "Berks County", "State": "Pennsylvania" },
  { "County": "Blair County", "State": "Pennsylvania" },
  { "County": "Bradford County", "State": "Pennsylvania" },
  { "County": "Bucks County", "State": "Pennsylvania" },
  { "County": "Butler County", "State": "Pennsylvania" },
  { "County": "Cambria County", "State": "Pennsylvania" },
  { "County": "Cameron County", "State": "Pennsylvania" },
  { "County": "Carbon County", "State": "Pennsylvania" },
  { "County": "Centre County", "State": "Pennsylvania" },
  { "County": "Chester County", "State": "Pennsylvania" },
  { "County": "Clarion County", "State": "Pennsylvania" },
  { "County": "Clearfield County", "State": "Pennsylvania" },
  { "County": "Clinton County", "State": "Pennsylvania" },
  { "County": "Columbia County", "State": "Pennsylvania" },
  { "County": "Crawford County", "State": "Pennsylvania" },
  { "County": "Cumberland County", "State": "Pennsylvania" },
  { "County": "Dauphin County", "State": "Pennsylvania" },
  { "County": "Delaware County", "State": "Pennsylvania" },
  { "County": "Elk County", "State": "Pennsylvania" },
  { "County": "Erie County", "State": "Pennsylvania" },
  { "County": "Fayette County", "State": "Pennsylvania" },
  { "County": "Forest County", "State": "Pennsylvania" },
  { "County": "Franklin County", "State": "Pennsylvania" },
  { "County": "Fulton County", "State": "Pennsylvania" },
  { "County": "Greene County", "State": "Pennsylvania" },
  { "County": "Huntingdon County", "State": "Pennsylvania" },
  { "County": "Indiana County", "State": "Pennsylvania" },
  { "County": "Jefferson County", "State": "Pennsylvania" },
  { "County": "Juniata County", "State": "Pennsylvania" },
  { "County": "Lackawanna County", "State": "Pennsylvania" },
  { "County": "Lancaster County", "State": "Pennsylvania" },
  { "County": "Lawrence County", "State": "Pennsylvania" },
  { "County": "Lebanon County", "State": "Pennsylvania" },
  { "County": "Lehigh County", "State": "Pennsylvania" },
  { "County": "Luzerne County", "State": "Pennsylvania" },
  { "County": "Lycoming County", "State": "Pennsylvania" },
  { "County": "McKean County", "State": "Pennsylvania" },
  { "County": "Mercer County", "State": "Pennsylvania" },
  { "County": "Mifflin County", "State": "Pennsylvania" },
  { "County": "Monroe County", "State": "Pennsylvania" },
  { "County": "Montgomery County", "State": "Pennsylvania" },
  { "County": "Montour County", "State": "Pennsylvania" },
  { "County": "Northampton County", "State": "Pennsylvania" },
  { "County": "Northumberland County", "State": "Pennsylvania" },
  { "County": "Perry County", "State": "Pennsylvania" },
  { "County": "Philadelphia County", "State": "Pennsylvania" },
  { "County": "Pike County", "State": "Pennsylvania" },
  { "County": "Potter County", "State": "Pennsylvania" },
  { "County": "Schuylkill County", "State": "Pennsylvania" },
  { "County": "Snyder County", "State": "Pennsylvania" },
  { "County": "Somerset County", "State": "Pennsylvania" },
  { "County": "Sullivan County", "State": "Pennsylvania" },
  { "County": "Susquehanna County", "State": "Pennsylvania" },
  { "County": "Tioga County", "State": "Pennsylvania" },
  { "County": "Union County", "State": "Pennsylvania" },
  { "County": "Venango County", "State": "Pennsylvania" },
  { "County": "Warren County", "State": "Pennsylvania" },
  { "County": "Washington County", "State": "Pennsylvania" },
  { "County": "Wayne County", "State": "Pennsylvania" },
  { "County": "Westmoreland County", "State": "Pennsylvania" },
  { "County": "Wyoming County", "State": "Pennsylvania" },
  { "County": "York County", "State": "Pennsylvania" }
]
